Metadata-Version: 2.1
Name: melctl-client-plugins-customer
Version: 1.2.0
Summary: Customers plugins for LuxProvide API command-line client
Home-page: https://github.com/LuxProvide/melctl-client-plugins-customer
Author: jpclipffel
License: UNKNOWN
Platform: UNKNOWN
License-File: LICENSE
